{
  "manifesto": [
    {
      "title": "子ども支援の所得制限撤廃",
      "reason": "「所得制限」という具体的な変数の「撤廃」という明確な制度変更を伴い客観的に検証可能であるため。",
      "quote_text": "あらゆる子ども支援の所得制限撤廃",
      "policy_id": "policy_043"
    },
    {
      "title": "「防衛三文書」の前倒し改定",
      "reason": "特定の政府文書の「改定」という具体的なアクションを指しており実施の有無が客観的に判断できるため。",
      "quote_text": "「防衛三文書」前倒し改定",
      "policy_id": "policy_126"
    },
    {
      "title": "インテリジェンス機関の設置",
      "reason": "新規の公的機関の設立という具体的な制度構築アクションを明言しておりその存否が客観的に確認可能なため。",
      "quote_text": "インテリジェンス機関設置",
      "policy_id": "policy_125"
    },
    {
      "title": "スパイ防止法の制定",
      "reason": "「新法の制定」という明確かつ具体的な政治的コミットメントであり法律の有無で検証可能であるため。",
      "quote_text": "スパイ防止法制定",
      "policy_id": "policy_045"
    },
    {
      "title": "日本版CFIUSの設置",
      "reason": "特定の新規制度の設立を明言しておりその存否が客観的に確認可能なため。",
      "quote_text": "日本版CFIUS(外国投資審査)の設置",
      "policy_id": "policy_002"
    }
  ],
  "not-manifesto": [
    {
      "title": "研究開発・競争力の強化",
      "reason": "「強化」という曖昧な表現であり実施の有無を客観的に判断できないため。",
      "quote_text": "17分野への戦略投資による研究開発・競争力強化(AI・半導体、量子、核融合、バイオ、航空、宇宙、造船等)"
    },
    {
      "title": "エネルギー適正化と電気代引き下げ",
      "reason": "「電気代引き下げ」はどの制度を操作するかが不明であり「適正化」も抽象的で検証不能であるため。",
      "quote_text": "原発再稼働・再生可能エネルギー適正化→安定供給、電気代引き下げ"
    },
    {
      "title": "商店街・産業の支援や活性化",
      "reason": "「活性化」「支援」は方向性を示すのみで具体的にどの変数を操作するのかが不明瞭であるため。",
      "quote_text": "商店街活性化、杉並のアニメ・デジタル産業支援"
    },
    {
      "title": "日本版DOGEによる歳出改革",
      "reason": "「歳出改革」は抽象的なスローガンであり具体的にどの予算や制度を変更するのかが全く特定されていないため。",
      "quote_text": "日本版DOGE(ドッジ)による大胆な歳出改革"
    },
    {
      "title": "光熱費値下げと負担軽減",
      "reason": "「値下げ」「負担軽減」のためにどの制度をどう変更するかが不明であり結果を述べているに過ぎないため。",
      "quote_text": "電気、ガス等光熱費値下げ、現役世代の負担軽減"
    },
    {
      "title": "マイナンバー活用による寄り添う支援",
      "reason": "「寄りそう支援」という抽象的なスローガンであり客観的な達成の観測が不可能なため。",
      "quote_text": "マイナンバー活用であなたに寄りそう支援実現"
    },
    {
      "title": "シニアの活躍支援",
      "reason": "「活躍支援」は抽象的なスローガンであり具体的な制度的裏付けが示されていないため。",
      "quote_text": "仕事で!地域で!シニアの活躍支援"
    },
    {
      "title": "いじめ対策厳格化",
      "reason": "「厳格化」は程度の問題でありいつ達成されたか第三者が客観的に判定できないため。",
      "quote_text": "いじめ対策厳格化"
    },
    {
      "title": "支援拡充と体験格差是正",
      "reason": "「拡充」「是正」は曖昧な方向性を示すのみで客観的に測定可能な条件の変更を伴わないため。",
      "quote_text": "障がい児・医療ケア児支援拡充、子どもの体験格差是正"
    },
    {
      "title": "サイバー・宇宙等新領域対応",
      "reason": "「対応」という曖昧な表現であり具体的な法的アクションが定義されていないため。",
      "quote_text": "サイバー・宇宙等新領域対応"
    },
    {
      "title": "経済的威圧への対抗",
      "reason": "「対抗」は曖昧な意気込みであり客観的に観測可能な制度変更を伴わないため。",
      "quote_text": "経済的威圧への対抗"
    },
    {
      "title": "在留資格の厳格管理と不正防止",
      "reason": "「厳格管理」は既存ルールの徹底にとどまり「不正防止」も目的にすぎず新規の制度変更を含まないため。",
      "quote_text": "外国人の在留資格厳格管理、マイナンバー活用で不正防止"
    },
    {
      "title": "政治資金の透明化とクリーンな運用",
      "reason": "「透明化」「クリーンな運用」は抽象的なスローガンであり制度の具体的な変更を示していないため。",
      "quote_text": "政治資金の透明化、クリーンな運用"
    },
    {
      "title": "世襲・派閥依存からの脱却と挑戦応援",
      "reason": "「脱却」「応援」という抽象的で曖昧な意気込みであり法律や制度への具体的な行動を伴わないため。",
      "quote_text": "世襲・派閥依存から脱却、女性・若者の挑戦を応援"
    }
  ]
}